Metadata-Version: 1.0
Name: limap
Version: 0.1
Summary: LimerBoy Mapper package, https://github.com/LimerBoy/PyMapper/
Home-page: UNKNOWN
Author: UNKNOWN
Author-email: clerksmo@protonmail.ch
License: UNKNOWN
Platform: UNKNOWN
